rowfind.py
rowfind-0.2.0.dist-info/LICENSE
rowfind-0.2.0.dist-info/METADATA
rowfind-0.2.0.dist-info/WHEEL
rowfind-0.2.0.dist-info/RECORD
