Metadata-Version: 2.1
Name: rowfind
Version: 0.2.0
Summary: Find points that make an equally spaced row on a 2D plane
Home-page: https://github.com/AnnikaV9/rowfind
License: MIT
Author: AnnikaV9
Author-email: carrot.moncher@gmail.com
Requires-Python: >=3.10,<4.0
Classifier: License :: OSI Approved :: MIT License
Classifier: Programming Language :: Python :: 3
Classifier: Programming Language :: Python :: 3.10
Classifier: Programming Language :: Python :: 3.11
Classifier: Programming Language :: Python :: 3.12
Classifier: Programming Language :: Python :: 3.13
Project-URL: Repository, https://github.com/AnnikaV9/rowfind
